<?xml version="1.0" encoding="UTF-8"?>
<objects serializationModel="Studio.02.02.00">
	<object class="EncodingSetting" id="{99e0c8bc-4dfa-4342-aa4e-ae8748da41fc}">
		<property name="encodingFormat">
			<value>3</value>
		</property>
		<property name="quality">
			<value>37</value>
		</property>
		<relationship name="platform">
			<destination>{0475cc15-086a-417c-8bed-e565abc3c3e0}</destination>
		</relationship>
		<relationship name="encodable">
			<destination>{0475cc15-086a-417c-8bed-e565abc3c3e0}</destination>
		</relationship>
	</object>
</objects>
